Workbook

Sheet Start here
A1: Moodius Aurelius: financial model
A2: Costs, cost of goods and postage, per-unit economics, scenarios, 90-day P&L and cash, unlock gates and other income streams. Built 21 Oct 2026 by Claude.
A4: Colour key
A5: Blue text = an input you can change
A6: Black text = a formula
A7: Green text = linked from another sheet
A8: Yellow fill = waiting on you
A10: Headline numbers (live) | B10: Conservative | C10: Base | D10: Optimistic | E10: Note
A11: Fixed costs per month £ (included set) | B11: ='Fixed costs'!$D$17 -> 28.224638 | C11: ='Fixed costs'!$D$17 -> 28.224638 | D11: ='Fixed costs'!$D$17 -> 28.224638 | E11: Metricool + domain + PO box by default.
A12: Fixed costs per month € | B12: ='Fixed costs'!$D$17*Inputs!$C$6 -> 32.458333 | C12: ='Fixed costs'!$D$17*Inputs!$C$6 -> 32.458333 | D12: ='Fixed costs'!$D$17*Inputs!$C$6 -> 32.458333 | E12: Lean target ≈ €20-25.
A13: Journal profit per sale £ (blended, after refunds) | B13: =Journals!$J$6 -> 10.160467 | C13: =Journals!$J$6 -> 10.160467 | D13: =Journals!$J$6 -> 10.160467 | E13: From the shop thread's prices and fees.
A14: Journal sales a month to cover fixed costs | B14: =Scenarios!$B$29 -> 2.7778879 | C14: =Scenarios!$C$29 -> 2.7778879 | D14: =Scenarios!$D$29 -> 2.7778879
A15: Revenue per 1,000 views £ (month-3 run rate) | B15: =Scenarios!$B$25 -> 0.226 | C15: =Scenarios!$C$25 -> 0.956 | D15: =Scenarios!$D$25 -> 4.152 | E15: Today, measured: £0 (nothing on sale).
A16: Views a month needed to cover fixed costs | B16: =Scenarios!$B$28 -> 163861.86 | C16: =Scenarios!$C$28 -> 39737.907 | D16: =Scenarios!$D$28 -> 9265.4797 | E16: Today: ~1,350 reel views a month.
A17: Journal sales over the 90 days | B17: =Scenarios!$B$35 -> 0.128058 | C17: =Scenarios!$C$35 -> 1.622208 | D17: =Scenarios!$D$35 -> 17.667936
A18: 90-day net result £ | B18: =Scenarios!$B$39 -> -83.098374 | C18: =Scenarios!$C$39 -> -66.670703 | D18: =Scenarios!$D$39 -> 102.2022 | E18: Excludes ads.
A19: €35 ad test: cost per guide sign-up £ (expensive to cheap clicks) | B19: =Ads!$B$11 -> 4.5 | C19: =Ads!$C$11 -> 2.75 | D19: =Ads!$D$11 -> 1 | E19: Worth about £0.10-0.41 each in journal profit (Scenarios).
A20: €35 ad test: cost per journal sale £ | B20: =Ads!$B$13 -> 84.375 | C20: =Ads!$C$13 -> 51.5625 | D20: =Ads!$D$13 -> 18.75 | E20: Break-even is the journal profit per sale.
A21: Gates met | B21: =Gates!$C$21 -> 1 | C21: =Gates!$D$21 -> 15 | E21: Met / total, Gates sheet.
A23: Sheets
A24: Inputs | B24: Every number, with type and source
A25: Fixed costs | B25: Monthly costs in £ and €, with approval status
A26: Journals | B26: Per-sale economics from the shop thread, plus a print edition
A27: Merch | B27: POD tee, print and notebook: cost of goods, postage UK/EU/US, Etsy fees, margin
A28: Ads | B28: €35 test maths, break-even cost per result, slot for your ad results
A29: Scenarios | B29: Conservative / base / optimistic, revenue per 1,000 views, break-even
A30: 90-day P&L | B30: Monthly P&L and cash, 2 Nov-31 Jan; pick the scenario in B3
A31: Rate card | B31: Brand-deal pricing tied to measured views; partner categories
A32: Other income | B32: Mentoring, membership, workshops, paid Substack, affiliates, brand deals, licensing: ranked
A33: Gates | B33: Thresholds that unlock each spend or stream, with live status
A34: 12-month plan | B34: Sequence of streams and spends
A35: Your inputs | B35: What only you can provide

Sheet Inputs
B1: Inputs: every number the model uses
B2: Blue = a value you can change. Yellow = waiting on you. Type says where it came from: Measured, Benchmark (with source), Assumption (not sourced, replace with real data), From shop thread, Plan, Surafel input.
B4: Input | C4: Value | D4: Unit | E4: Type | F4: Source / note
B5: Currency
B6: Euros per £1 | C6: 1.15 | D6: € per £ | E6: Assumption | F6: Approximate rate on 21 Oct 2026. Update from your bank or xe.com; every EUR column follows it.
B7: Pounds per $1 | C7: 0.75 | D7: £ per $ | E7: Assumption | F7: Approximate rate on 21 Oct 2026. Used to convert US-dollar supplier and ad benchmarks.
B8: Measured today (Metricool, @moodiusaurelius, pulled 21 Oct 2026, window 22 Sep-21 Oct)
B9: Instagram followers now | C9: 14 | D9: followers | E9: Measured | F9: Metricool IGEV01 on 21 Oct 2026 (was 3 on 4 Oct, account-snapshot-2026-10-04.md).
B10: Reel views, last 30 days | C10: 1347 | D10: views | E10: Measured | F10: Metricool IGEV23, sum of daily values 22 Sep-21 Oct 2026.
B11: All account views, last 30 days | C11: 2252 | D11: views | E11: Measured | F11: Metricool IGEV05, organic + paid, same window.
B12: Median views per reel (baseline) | C12: 130 | D12: views | E12: Measured | F12: strategy/09-scaling-roadmap.md baseline (~130). Feed posts ~53 per 20 Oct insights.
B13: Best single day of reel views (proxy for best reel) | C13: 278 | D13: views | E13: Measured | F13: Metricool IGEV23, 12 Oct 2026. Daily total, so a proxy, not a per-reel figure.
B14: Share of views from non-followers | C14: 0.93 | D14: % | E14: Measured | F14: Instagram insights screenshots, 20 Oct 2026.
B15: Reel shares (sends), last 30 days | C15: 6 | D15: shares | E15: Measured | F15: Metricool IGEV39, same window. Sends ≈ 0 per post.
B16: Free guide / newsletter sign-ups so far | C16: 0 | D16: people | E16: Measured | F16: No list is live yet. Update weekly once the guide page is live.
B17: Journal orders so far | C17: 0 | D17: orders | E17: Measured | F17: Shop is in test mode. Update from the back office once live.
B18: Substack free subscribers | C18: 0 | D18: people | E18: Measured | F18: Publication not created yet (first essay planned 5 Nov 2026).
B19: Comments + story replies per week | C19: 0 | D19: per week | E19: Surafel input | F19: Not measured yet. Fill in from Instagram; drives the VPS/Claude API gate.
B20: Shop live? (1 = yes, 0 = no) | C20: 0 | D20: flag | E20: Surafel input | F20: Set to 1 the day you say 'go live' on the storefront.
B21: Journals and digital products (from the digital-products thread, business/pricing/margins.py)
B22: VAT assumed inside every digital price | C22: 0.2 | D22: % | E22: From shop thread | F22: Conservative: UK e-publications are zero-rated, but fill-in journals may not qualify.
B23: Stripe Managed Payments fee | C23: 0.035 | D23: % of sale | E23: From shop thread | F23: support.stripe.com/questions/managed-payments-pricing
B24: Stripe UK card % | C24: 0.015 | D24: % of sale | E24: From shop thread | F24: stripe.com/gb/pricing, checked 21 Oct 2026
B25: Stripe EEA card % (incl. 2% FX) | C25: 0.045 | D25: % of sale | E25: From shop thread | F25: 2.5% + 2% currency conversion, stripe.com/gb/pricing
B26: Stripe international card % (incl. 2% FX) | C26: 0.0515 | D26: % of sale | E26: From shop thread | F26: 3.15% + 2% currency conversion, stripe.com/gb/pricing
B27: Stripe fixed fee per payment | C27: 0.2 | D27: £ | E27: From shop thread | F27: stripe.com/gb/pricing
B28: Value of your time for personalised items | C28: 15 | D28: £/hour | E28: From shop thread | F28: margins.py HOUR
B29: Refund rate | C29: 0.03 | D29: % of sales | E29: Assumption | F29: Suggested by the shop thread; not sourced. Replace with real refunds after 25 orders.
B30: Buyer mix: UK cards | C30: 0.6 | D30: % | E30: Assumption | F30: No sales yet and audience location unknown. Replace with Stripe data.
B31: Buyer mix: EEA cards | C31: 0.2 | D31: % | E31: Assumption | F31: As above.
B32: Buyer mix: international cards | C32: 0.2 | D32: % | E32: Assumption | F32: As above. The three mix cells should add to 100%.
B33: Journal orders before the £29 bundle is built | C33: 25 | D33: orders | E33: From shop thread | F33: business/funnel/bundle-plan.md (or 6 weeks on sale).
B34: Paid Instagram ads (benchmarks, replace with your own results)
B35: Suggested first test | C35: 35 | D35: € | E35: Plan | F35: growth-and-monetisation-plan.md: €5/day x 7 days on one winning reel. Needs your OK.
B36: Cost per link click, low | C36: 0.4 | D36: $ | E36: Benchmark | F36: topgrowthmarketing.com/instagram-ads-cost (2026, aggregated; no UK split).
B37: Cost per link click, high | C37: 1.8 | D37: $ | E37: Benchmark | F37: Same source, destination clicks $0.50-1.80.
B38: Reels CPM, low | C38: 4 | D38: $ per 1,000 | E38: Benchmark | F38: Ryze.AI via topgrowthmarketing.com (2026), consumer verticals.
B39: Reels CPM, high | C39: 8 | D39: $ per 1,000 | E39: Benchmark | F39: Same source.
B40: Cost per follower (boost), low | C40: 0.3 | D40: £ | E40: Assumption | F40: No reliable published benchmark found. Replace with your ad screenshot.
B41: Cost per follower (boost), high | C41: 1.5 | D41: £ | E41: Assumption | F41: As above.
B42: Merch (print-on-demand, no inventory)
B43: Etsy listing fee per sale | C43: 0.2 | D43: $ | E43: Benchmark | F43: Etsy fees policy (etsy.com/legal/fees). Check before launch.
B44: Etsy transaction fee | C44: 0.065 | D44: % of item + shipping | E44: Benchmark | F44: Etsy fees policy.
B45: Etsy Payments processing (UK) | C45: 0.04 | D45: % of order | E45: Benchmark | F45: Etsy Payments UK: 4% + £0.20.
B46: Etsy Payments fixed fee (UK) | C46: 0.2 | D46: £ | E46: Benchmark | F46: As above.
B47: VAT charged on Etsy fees (UK seller, not VAT-registered) | C47: 0.2 | D47: % | E47: Benchmark | F47: Etsy charges UK VAT on its fees to UK sellers.
B48: Returns / reprint allowance | C48: 0.05 | D48: % of retail | E48: Assumption | F48: POD suppliers reprint their own misprints; this covers change-of-mind returns you absorb.
B49: One-off sample orders before launch | C49: 45 | D49: £ | E49: Assumption | F49: 3 items x ~£15 incl. shipping. A spend: needs your OK.
B50: Other income streams
B51: Bookshop.org affiliate commission | C51: 0.1 | D51: % of order | E51: Benchmark | F51: supadu.com/blogs/news-and-views/bookshop-org (10% to affiliates).
B52: Average affiliate book order | C52: 12 | D52: £ | E52: Assumption | F52: One paperback. Not sourced.
B53: Affiliate click to order | C53: 0.05 | D53: % | E53: Assumption | F53: Not sourced; replace after the Week 3 affiliate experiment.
B54: Paid Substack price | C54: 5 | D54: £/month | E54: Assumption | F54: Substack minimum is $5/month (bestwriting.com/substack-statistics).
B55: Substack platform fee | C55: 0.1 | D55: % of payment | E55: Benchmark | F55: substack/10-costs-and-apis.md and bestwriting.com.
B56: Stripe fee on Substack payments | C56: 0.029 | D56: % of payment | E56: Benchmark | F56: substack/10-costs-and-apis.md (2.9% + €0.30).
B57: Stripe fixed fee on Substack payments | C57: 0.25 | D57: £ | E57: Benchmark | F57: €0.30 converted, rounded.
B58: Free to paid Substack conversion | C58: 0.03 | D58: % | E58: Benchmark | F58: Average 3%, niche 4-10% (bestwriting.com, citing reallygoodbusinessideas.com).
B59: Creator rate CPM, low | C59: 5 | D59: $ per 1,000 views | E59: Benchmark | F59: influee.co Instagram influencer pricing 2026, nano/micro $5-15 CPM.
B60: Creator rate CPM, high | C60: 15 | D60: $ per 1,000 views | E60: Benchmark | F60: Same source.
B61: Nano creator (1k-10k followers) reel, low | C61: 50 | D61: $ | E61: Benchmark | F61: Same source: nano reel $50-300.
B62: Nano creator (1k-10k followers) reel, high | C62: 300 | D62: $ | E62: Benchmark | F62: Same source.
... B72: KDP printing cost, ~120 pp black and white | C72: 2.29 | D72: £ | E72: Assumption | F72: Estimated, check the KDP printing-cost calculator.
B73: Cash
B74: Cash set aside for the business on 1 Nov | C74: 0 | D74: £ | E74: Surafel input | F74: Put your starting budget here; the cash view shows if it ever goes below zero.
B75: Share of a month's sales paid out the next month | C75: 0.25 | D75: % | E75: Assumption | F75: Roughly a 7-day payout delay. Replace with your Stripe payout schedule.
B76: Month the shop starts selling (1 = Nov, 2 = Dec, 3 = Jan) | C76: 1 | D76: month | E76: Surafel input | F76: Set to 2 if the shop isn't live by the end of November.

Sheet Fixed costs
A1: Fixed monthly costs (GBP with EUR alongside)
A2: Include = 1 counts the cost in the P&L. Costs marked 'Needs your OK' are set as they would be once approved; set Include to 0 to see the model without them.
A4: Item | B4: Currency | C4: Amount (native) | D4: Monthly £ | E4: Monthly € | F4: Include | G4: Status | H4: Note
A5: Metricool Starter (scheduling + analytics) | B5: EUR | C5: 20 | D5: =IF(B5="GBP",C5,C5/Inputs!$C$6) -> 17.391304 | E5: =D5*Inputs!$C$6 -> 20 | F5: 1 | G5: Active (paid 21 Oct) | H5: Monthly plan; Instagram + Facebook now, Threads/Pinterest when connected.
A6: Domain for the shop | B6: GBP | C6: 10 | D6: =IF(B6="GBP",C6,C6/Inputs!$C$6)/12 -> 0.83333333 | E6: =D6*Inputs!$C$6 -> 0.95833333 | F6: 1 | G6: Needs your OK | H6: About £10 a year, shown per month. Paid upfront in the cash view.
A7: PO box / virtual address | B7: GBP | C7: 10 | D7: =IF(B7="GBP",C7,C7/Inputs!$C$6) -> 10 | E7: =D7*Inputs!$C$6 -> 11.5 | F7: 1 | G7: Needs your OK | H7: £5-15 a month, midpoint. Legally needed on the shop's legal pages and in marketing emails.
A8: VPS for comment agent + n8n | B8: EUR | C8: 5 | D8: =IF(B8="GBP",C8,C8/Inputs!$C$6) -> 4.3478261 | E8: =D8*Inputs!$C$6 -> 5 | F8: 0 | G8: Needs your OK | H8: €4-6 a month (community-agent/docs/04). Off until the comments gate is met.
A9: Claude API for comment replies | B9: EUR | C9: 5 | D9: =IF(B9="GBP",C9,C9/Inputs!$C$6) -> 4.3478261 | E9: =D9*Inputs!$C$6 -> 5 | F9: 0 | G9: Needs your OK | H9: €1-10 a month depending on model and volume. Runs on the VPS, so same gate.
A10: Cloudflare Pages + D1 + R2 (shop) | B10: GBP | C10: 0 | D10: =IF(B10="GBP",C10,C10/Inputs!$C$6) -> 0 | E10: =D10*Inputs!$C$6 -> 0 | F10: 1 | G10: Free tier | H10: Commercial use allowed on the free tier.
A11: Resend email | B11: GBP | C11: 0 | D11: =IF(B11="GBP",C11,C11/Inputs!$C$6) -> 0 | E11: =D11*Inputs!$C$6 -> 0 | F11: 1 | G11: Free tier | H11: Free up to 3,000 emails a month.
A12: Substack | B12: GBP | C12: 0 | D12: =IF(B12="GBP",C12,C12/Inputs!$C$6) -> 0 | E12: =D12*Inputs!$C$6 -> 0 | F12: 1 | G12: Free | H12: Free to publish; 10% + Stripe only if paid subscriptions are switched on.
A13: Stripe (Managed Payments) | B13: GBP | C13: 0 | D13: =IF(B13="GBP",C13,C13/Inputs!$C$6) -> 0 | E13: =D13*Inputs!$C$6 -> 0 | F13: 1 | G13: No monthly fee | H13: Per-sale fees sit in the unit economics, not here.
A14: GitHub, Kit free tier, Canva free | B14: GBP | C14: 0 | D14: =IF(B14="GBP",C14,C14/Inputs!$C$6) -> 0 | E14: =D14*Inputs!$C$6 -> 0 | F14: 1 | G14: Free
A15: Etsy shop for merch (later) | B15: GBP | C15: 0 | D15: =IF(B15="GBP",C15,C15/Inputs!$C$6) -> 0 | E15: =D15*Inputs!$C$6 -> 0 | F15: 0 | G15: Not started | H15: No monthly fee on Etsy Standard; fees are per sale (Merch sheet).
A17: Total included in the model | D17: =SUMPRODUCT(D5:D15,F5:F15) -> 28.224638 | E17: =D17*Inputs!$C$6 -> 32.458333
A18: Total if every cost listed is switched on | D18: =SUM(D5:D15) -> 36.92029 | E18: =D18*Inputs!$C$6 -> 42.458333
A19: Lean budget target (upper end) | D19: =E19/Inputs!$C$6 -> 21.73913 | E19: 25
A20: Headroom (included vs target) | D20: =D19-D17 -> -6.4855072 | E20: =E19-E17 -> -7.4583333

Sheet Journals
A1: Journals and digital products: per-sale economics
A2: Prices and fees are the digital-products thread's (business/pricing/margins.py). Recomputed here with formulas; column L shows margins.csv so you can see both agree. Digital cost of goods is £0 (delivery runs on free tiers).
A4: Product | B4: Price £ (VAT incl.) | C4: Minutes of your time | D4: VAT £ | E4: Fees UK £ | F4: Profit UK £ | G4: Profit EEA £ | H4: Profit intl £ | I4: Blended profit £ | J4: After refunds £ | K4: Margin (after refunds) | L4: margins.csv UK profit £ | M4: Status
A5: Seven Days of Honest Reflection (free guide) | B5: 0 | C5: 0 | D5: =B5-B5/(1+Inputs!$C$22) -> 0 | E5: =IF(B5=0,0,B5*(Inputs!$C$24+Inputs!$C$23)+Inputs!$C$27) -> 0 | F5: =IF(B5=0,0,B5-D5-E5-C5/60*Inputs!$C$28) -> 0 | G5: =IF(B5=0,0,B5-D5-(B5*(Inputs!$C$25+Inputs!$C$23)+Inputs!$C$27)-C5/60*Inputs!$C$28) -> 0 | H5: =IF(B5=0,0,B5-D5-(B5*(Inputs!$C$26+Inputs!$C$23)+Inputs!$C$27)-C5/60*Inputs!$C$28) -> 0 | I5: =F5*Inputs!$C$30+G5*Inputs!$C$31+H5*Inputs!$C$32 -> 0 | J5: =I5-B5*Inputs!$C$29 -> 0 | K5: =IF(B5=0,0,J5/B5) -> 0 | L5: 0 | M5: Live
A6: The Unexamined Self (journal) | B6: 14 | C6: 0 | D6: =B6-B6/(1+Inputs!$C$22) -> 2.3333333 | E6: =IF(B6=0,0,B6*(Inputs!$C$24+Inputs!$C$23)+Inputs!$C$27) -> 0.9 | F6: =IF(B6=0,0,B6-D6-E6-C6/60*Inputs!$C$28) -> 10.766667 | G6: =IF(B6=0,0,B6-D6-(B6*(Inputs!$C$25+Inputs!$C$23)+Inputs!$C$27)-C6/60*Inputs!$C$28) -> 10.346667 | H6: =IF(B6=0,0,B6-D6-(B6*(Inputs!$C$26+Inputs!$C$23)+Inputs!$C$27)-C6/60*Inputs!$C$28) -> 10.255667 | I6: =F6*Inputs!$C$30+G6*Inputs!$C$31+H6*Inputs!$C$32 -> 10.580467 | J6: =I6-B6*Inputs!$C$29 -> 10.160467 | K6: =IF(B6=0,0,J6/B6) -> 0.72574762 | L6: 10.77 | M6: Live
A7: Themed 14-day journal (one per highlight) | B7: 6 | C7: 0 | D7: =B7-B7/(1+Inputs!$C$22) -> 1 | E7: =IF(B7=0,0,B7*(Inputs!$C$24+Inputs!$C$23)+Inputs!$C$27) -> 0.5 | F7: =IF(B7=0,0,B7-D7-E7-C7/60*Inputs!$C$28) -> 4.5 | G7: =IF(B7=0,0,B7-D7-(B7*(Inputs!$C$25+Inputs!$C$23)+Inputs!$C$27)-C7/60*Inputs!$C$28) -> 4.32 | H7: =IF(B7=0,0,B7-D7-(B7*(Inputs!$C$26+Inputs!$C$23)+Inputs!$C$27)-C7/60*Inputs!$C$28) -> 4.281 | I7: =F7*Inputs!$C$30+G7*Inputs!$C$31+H7*Inputs!$C$32 -> 4.4202 | J7: =I7-B7*Inputs!$C$29 -> 4.2402 | K7: =IF(B7=0,0,J7/B7) -> 0.7067 | L7: 4.5 | M7: Planned
A8: Workbook (Feeling Clearly / How You Attach / What You Live By) | B8: 9 | C8: 0 | D8: =B8-B8/(1+Inputs!$C$22) -> 1.5 | E8: =IF(B8=0,0,B8*(Inputs!$C$24+Inputs!$C$23)+Inputs!$C$27) -> 0.65 | F8: =IF(B8=0,0,B8-D8-E8-C8/60*Inputs!$C$28) -> 6.85 | G8: =IF(B8=0,0,B8-D8-(B8*(Inputs!$C$25+Inputs!$C$23)+Inputs!$C$27)-C8/60*Inputs!$C$28) -> 6.58 | H8: =IF(B8=0,0,B8-D8-(B8*(Inputs!$C$26+Inputs!$C$23)+Inputs!$C$27)-C8/60*Inputs!$C$28) -> 6.5215 | I8: =F8*Inputs!$C$30+G8*Inputs!$C$31+H8*Inputs!$C$32 -> 6.7303 | J8: =I8-B8*Inputs!$C$29 -> 6.4603 | K8: =IF(B8=0,0,J8/B8) -> 0.71781111 | L8: 6.85 | M8: Planned
A9: The Examined Life bundle | B9: 29 | C9: 0 | D9: =B9-B9/(1+Inputs!$C$22) -> 4.8333333 | E9: =IF(B9=0,0,B9*(Inputs!$C$24+Inputs!$C$23)+Inputs!$C$27) -> 1.65 | F9: =IF(B9=0,0,B9-D9-E9-C9/60*Inputs!$C$28) -> 22.516667 | G9: =IF(B9=0,0,B9-D9-(B9*(Inputs!$C$25+Inputs!$C$23)+Inputs!$C$27)-C9/60*Inputs!$C$28) -> 21.646667 | H9: =IF(B9=0,0,B9-D9-(B9*(Inputs!$C$26+Inputs!$C$23)+Inputs!$C$27)-C9/60*Inputs!$C$28) -> 21.458167 | I9: =F9*Inputs!$C$30+G9*Inputs!$C$31+H9*Inputs!$C$32 -> 22.130967 | J9: =I9-B9*Inputs!$C$29 -> 21.260967 | K9: =IF(B9=0,0,J9/B9) -> 0.73313678 | L9: 22.52 | M9: Planned
A10: Bundle upgrade for journal buyers | B10: 15 | C10: 0 | D10: =B10-B10/(1+Inputs!$C$22) -> 2.5 | E10: =IF(B10=0,0,B10*(Inputs!$C$24+Inputs!$C$23)+Inputs!$C$27) -> 0.95 | F10: =IF(B10=0,0,B10-D10-E10-C10/60*Inputs!$C$28) -> 11.55 | G10: =IF(B10=0,0,B10-D10-(B10*(Inputs!$C$25+Inputs!$C$23)+Inputs!$C$27)-C10/60*Inputs!$C$28) -> 11.1 | H10: =IF(B10=0,0,B10-D10-(B10*(Inputs!$C$26+Inputs!$C$23)+Inputs!$C$27)-C10/60*Inputs!$C$28) -> 11.0025 | I10: =F10*Inputs!$C$30+G10*Inputs!$C$31+H10*Inputs!$C$32 -> 11.3505 | J10: =I10-B10*Inputs!$C$29 -> 10.9005 | K10: =IF(B10=0,0,J10/B10) -> 0.7267 | L10: 11.55 | M10: Planned
A11: Personalised journal (journal + personalisation) | B11: 19 | C11: 3 | D11: =B11-B11/(1+Inputs!$C$22) -> 3.1666667 | E11: =IF(B11=0,0,B11*(Inputs!$C$24+Inputs!$C$23)+Inputs!$C$27) -> 1.15 | F11: =IF(B11=0,0,B11-D11-E11-C11/60*Inputs!$C$28) -> 13.933333 | G11: =IF(B11=0,0,B11-D11-(B11*(Inputs!$C$25+Inputs!$C$23)+Inputs!$C$27)-C11/60*Inputs!$C$28) -> 13.363333 | H11: =IF(B11=0,0,B11-D11-(B11*(Inputs!$C$26+Inputs!$C$23)+Inputs!$C$27)-C11/60*Inputs!$C$28) -> 13.239833 | I11: =F11*Inputs!$C$30+G11*Inputs!$C$31+H11*Inputs!$C$32 -> 13.680633 | J11: =I11-B11*Inputs!$C$29 -> 13.110633 | K11: =IF(B11=0,0,J11/B11) -> 0.69003333 | L11: 13.93 | M11: Built (test mode)
A12: Gift edition (personalised + gift page + chosen send date) | B12: 22 | C12: 4 | D12: =B12-B12/(1+Inputs!$C$22) -> 3.6666667 | E12: =IF(B12=0,0,B12*(Inputs!$C$24+Inputs!$C$23)+Inputs!$C$27) -> 1.3 | F12: =IF(B12=0,0,B12-D12-E12-C12/60*Inputs!$C$28) -> 16.033333 | G12: =IF(B12=0,0,B12-D12-(B12*(Inputs!$C$25+Inputs!$C$23)+Inputs!$C$27)-C12/60*Inputs!$C$28) -> 15.373333 | H12: =IF(B12=0,0,B12-D12-(B12*(Inputs!$C$26+Inputs!$C$23)+Inputs!$C$27)-C12/60*Inputs!$C$28) -> 15.230333 | I12: =F12*Inputs!$C$30+G12*Inputs!$C$31+H12*Inputs!$C$32 -> 15.740733 | J12: =I12-B12*Inputs!$C$29 -> 15.080733 | K12: =IF(B12=0,0,J12/B12) -> 0.68548788 | L12: 16.03 | M12: Built (test mode)
A13: Personalised bundle | B13: 34 | C13: 3 | D13: =B13-B13/(1+Inputs!$C$22) -> 5.6666667 | E13: =IF(B13=0,0,B13*(Inputs!$C$24+Inputs!$C$23)+Inputs!$C$27) -> 1.9 | F13: =IF(B13=0,0,B13-D13-E13-C13/60*Inputs!$C$28) -> 25.683333 | G13: =IF(B13=0,0,B13-D13-(B13*(Inputs!$C$25+Inputs!$C$23)+Inputs!$C$27)-C13/60*Inputs!$C$28) -> 24.663333 | H13: =IF(B13=0,0,B13-D13-(B13*(Inputs!$C$26+Inputs!$C$23)+Inputs!$C$27)-C13/60*Inputs!$C$28) -> 24.442333 | I13: =F13*Inputs!$C$30+G13*Inputs!$C$31+H13*Inputs!$C$32 -> 25.231133 | J13: =I13-B13*Inputs!$C$29 -> 24.211133 | K13: =IF(B13=0,0,J13/B13) -> 0.71209216 | L13: 25.68 | M13: Planned
A15: Future print edition (Amazon KDP paperback, no inventory)
A16: List price £ | B16: =Inputs!$C$70 -> 12.99
A17: Royalty (60% of list) minus printing cost = profit per copy £ | B17: =Inputs!$C$70*Inputs!$C$71-Inputs!$C$72 -> 5.504
A18: Cost of goods per copy £ (printing, deducted by Amazon) | B18: =Inputs!$C$72 -> 2.29
A19: Postage: Amazon ships; buyer pays or Prime covers it. You hold no stock. A printed personalised paperback (shop thread idea) would cost ~£3-4 to print + £3-4 UK post at ~£24-27, and can't use Managed Payments (digital only).
A21: Check: rows where the recomputed UK profit differs from margins.csv by more than 1p | B21: =SUMPRODUCT(--(ABS(F5:F13-L5:L13)>0.011)) -> 0

Sheet Merch
A1: Merch plan: print-on-demand, cost of goods and postage by region
A2: A plan only: no store or listings exist. Default channel is Etsy + a POD supplier (Printful shown; Printify or Gelato are alternatives) because Etsy collects UK/EU VAT on your behalf as the marketplace. Supplier choice is yours.
A4: Minimal typographic tee (Bella+Canvas 3001, one front print, Ember accent)
A5: Line (per order of one item) | B5: UK | C5: EU | D5: US | F5: Source / note
A6: Retail price £ (what the buyer pays for the item) | B6: 28 | C6: 28 | D6: 28 | F6: Assumption: priced for a premium minimal brand. Not sourced.
A7: Shipping charged to buyer £ | B7: 3.95 | C7: 5.95 | D7: 6.95 | F7: Assumption: set to roughly cover postage.
A8: Revenue £ | B8: =B6+B7 -> 31.95 | C8: =C6+C7 -> 33.95 | D8: =D6+D7 -> 34.95
A9: Supplier base cost (cost of goods) $ | B9: 12.95 | C9: 12.95 | D9: 12.95 | F9: Printful base on Free plan, $12.95 (podvector.ai, May 2026). Shipping UK/US $3.99, EU $4.99 first item.
A10: Cost of goods £ | B10: =B9*Inputs!$C$7 -> 9.7125 | C10: =C9*Inputs!$C$7 -> 9.7125 | D10: =D9*Inputs!$C$7 -> 9.7125 | F10: Converted at the Inputs rate.
A11: Postage (supplier shipping) £ | B11: =3.99*Inputs!$C$7 -> 2.9925 | C11: =4.99*Inputs!$C$7 -> 3.7425 | D11: =3.99*Inputs!$C$7 -> 2.9925 | F11: Supplier shipping rates; packaging is included by POD suppliers.
A12: Branded packaging / insert card £ | B12: 0 | C12: 0 | D12: 0 | F12: Assumption: £0, plain supplier packaging. Add ~£0.50-1 if you want inserts.
A13: Etsy listing fee £ | B13: =Inputs!$C$43*Inputs!$C$7 -> 0.15 | C13: =Inputs!$C$43*Inputs!$C$7 -> 0.15 | D13: =Inputs!$C$43*Inputs!$C$7 -> 0.15
A14: Etsy transaction fee £ | B14: =B8*Inputs!$C$44 -> 2.07675 | C14: =C8*Inputs!$C$44 -> 2.20675 | D14: =D8*Inputs!$C$44 -> 2.27175 | F14: 6.5% of item + shipping.
A15: Etsy Payments processing £ | B15: =B8*Inputs!$C$45+Inputs!$C$46 -> 1.478 | C15: =C8*Inputs!$C$45+Inputs!$C$46 -> 1.558 | D15: =D8*Inputs!$C$45+Inputs!$C$46 -> 1.598 | F15: 4% + £0.20.
A16: VAT on Etsy fees £ | B16: =(B13+B14+B15)*Inputs!$C$47 -> 0.74095 | C16: =(C13+C14+C15)*Inputs!$C$47 -> 0.78295 | D16: =(D13+D14+D15)*Inputs!$C$47 -> 0.80395 | F16: 20% on Etsy's fees.
A17: Returns / reprint allowance £ | B17: =B6*Inputs!$C$48 -> 1.4 | C17: =C6*Inputs!$C$48 -> 1.4 | D17: =D6*Inputs!$C$48 -> 1.4 | F17: Allowance on retail price.
A18: Total cost £ | B18: =B10+B11+B12+B13+B14+B15+B16+B17 -> 18.5507 | C18: =C10+C11+C12+C13+C14+C15+C16+C17 -> 19.5527 | D18: =D10+D11+D12+D13+D14+D15+D16+D17 -> 18.9287
A19: Contribution per order £ | B19: =B8-B18 -> 13.3993 | C19: =C8-C18 -> 14.3973 | D19: =D8-D18 -> 16.0213
A20: Margin on revenue | B20: =IF(B8=0,0,B19/B8) -> 0.41938341 | C20: =IF(C8=0,0,C19/C8) -> 0.42407364 | D20: =IF(D8=0,0,D19/D8) -> 0.45840629
A21: Same order on your own site with Stripe (no Etsy fees) £ | B21: =B8-B10-B11-B12-(B8*Inputs!$C$24+Inputs!$C$27)-B17 -> 17.16575 | C21: =C8-C10-C11-C12-(C8*Inputs!$C$25+Inputs!$C$27)-C17 -> 17.36725 | D21: =D8-D10-D11-D12-(D8*Inputs!$C$26+Inputs!$C$27)-D17 -> 18.845075 | F21: Higher margin, but you then handle VAT on goods sold to EU buyers yourself. Etsy first.
A23: Art print 12x16 in, enhanced matte (quote + Ember rule)
A24: Line (per order of one item) | B24: UK | C24: EU | D24: US | F24: Source / note
A25: Retail price £ (what the buyer pays for the item) | B25: 22 | C25: 22 | D25: 22 | F25: Assumption: priced for a premium minimal brand. Not sourced.
A26: Shipping charged to buyer £ | B26: 3.95 | C26: 5.95 | D26: 6.95 | F26: Assumption: set to roughly cover postage.
A27: Revenue £ | B27: =B25+B26 -> 25.95 | C27: =C25+C26 -> 27.95 | D27: =D25+D26 -> 28.95
A28: Supplier base cost (cost of goods) $ | B28: 10.95 | C28: 10.95 | D28: 10.95 | F28: Printful base $10.95; shipping UK £4.99, EU €5.49, US $4.99 (podvector.ai, May 2026).
A29: Cost of goods £ | B29: =B28*Inputs!$C$7 -> 8.2125 | C29: =C28*Inputs!$C$7 -> 8.2125 | D29: =D28*Inputs!$C$7 -> 8.2125 | F29: Converted at the Inputs rate.
A30: Postage (supplier shipping) £ | B30: =4.99 -> 4.99 | C30: =5.49/Inputs!$C$6 -> 4.773913 | D30: =4.99*Inputs!$C$7 -> 3.7425 | F30: Supplier shipping rates; packaging is included by POD suppliers.
A31: Branded packaging / insert card £ | B31: 0 | C31: 0 | D31: 0 | F31: Assumption: £0, plain supplier packaging. Add ~£0.50-1 if you want inserts.
A32: Etsy listing fee £ | B32: =Inputs!$C$43*Inputs!$C$7 -> 0.15 | C32: =Inputs!$C$43*Inputs!$C$7 -> 0.15 | D32: =Inputs!$C$43*Inputs!$C$7 -> 0.15
A33: Etsy transaction fee £ | B33: =B27*Inputs!$C$44 -> 1.68675 | C33: =C27*Inputs!$C$44 -> 1.81675 | D33: =D27*Inputs!$C$44 -> 1.88175 | F33: 6.5% of item + shipping.
A34: Etsy Payments processing £ | B34: =B27*Inputs!$C$45+Inputs!$C$46 -> 1.238 | C34: =C27*Inputs!$C$45+Inputs!$C$46 -> 1.318 | D34: =D27*Inputs!$C$45+Inputs!$C$46 -> 1.358 | F34: 4% + £0.20.
A35: VAT on Etsy fees £ | B35: =(B32+B33+B34)*Inputs!$C$47 -> 0.61495 | C35: =(C32+C33+C34)*Inputs!$C$47 -> 0.65695 | D35: =(D32+D33+D34)*Inputs!$C$47 -> 0.67795 | F35: 20% on Etsy's fees.
A36: Returns / reprint allowance £ | B36: =B25*Inputs!$C$48 -> 1.1 | C36: =C25*Inputs!$C$48 -> 1.1 | D36: =D25*Inputs!$C$48 -> 1.1 | F36: Allowance on retail price.
A37: Total cost £ | B37: =B29+B30+B31+B32+B33+B34+B35+B36 -> 17.9922 | C37: =C29+C30+C31+C32+C33+C34+C35+C36 -> 18.028113 | D37: =D29+D30+D31+D32+D33+D34+D35+D36 -> 17.1227
A38: Contribution per order £ | B38: =B27-B37 -> 7.9578 | C38: =C27-C37 -> 9.921887 | D38: =D27-D37 -> 11.8273
A39: Margin on revenue | B39: =IF(B27=0,0,B38/B27) -> 0.30665896 | C39: =IF(C27=0,0,C38/C27) -> 0.35498701 | D39: =IF(D27=0,0,D38/D27) -> 0.40854231
A40: Same order on your own site with Stripe (no Etsy fees) £ | B40: =B27-B29-B30-B31-(B27*Inputs!$C$24+Inputs!$C$27)-B36 -> 11.05825 | C40: =C27-C29-C30-C31-(C27*Inputs!$C$25+Inputs!$C$27)-C36 -> 12.405837 | D40: =D27-D29-D30-D31-(D27*Inputs!$C$26+Inputs!$C$27)-D36 -> 14.204075 | F40: Higher margin, but you then handle VAT on goods sold to EU buyers yourself. Etsy first.
A42: Hardcover lined notebook (Slate cover, small Ember mark)
A43: Line (per order of one item) | B43: UK | C43: EU | D43: US | F43: Source / note
A44: Retail price £ (what the buyer pays for the item) | B44: 22 | C44: 22 | D44: 22 | F44: Assumption: priced for a premium minimal brand. Not sourced.
A45: Shipping charged to buyer £ | B45: 3.95 | C45: 5.95 | D45: 6.95 | F45: Assumption: set to roughly cover postage.
A46: Revenue £ | B46: =B44+B45 -> 25.95 | C46: =C44+C45 -> 27.95 | D46: =D44+D45 -> 28.95
A47: Supplier base cost (cost of goods) $ | B47: 15 | C47: 15 | D47: 15 | F47: ESTIMATE: Printful's page shows no price without login. Check base and shipping in the supplier dashboard.
A48: Cost of goods £ | B48: =B47*Inputs!$C$7 -> 11.25 | C48: =C47*Inputs!$C$7 -> 11.25 | D48: =D47*Inputs!$C$7 -> 11.25 | F48: Converted at the Inputs rate.
A49: Postage (supplier shipping) £ | B49: =5.99*Inputs!$C$7 -> 4.4925 | C49: =5.99*Inputs!$C$7 -> 4.4925 | D49: =5.99*Inputs!$C$7 -> 4.4925 | F49: Supplier shipping rates; packaging is included by POD suppliers.
A50: Branded packaging / insert card £ | B50: 0 | C50: 0 | D50: 0 | F50: Assumption: £0, plain supplier packaging. Add ~£0.50-1 if you want inserts.
A51: Etsy listing fee £ | B51: =Inputs!$C$43*Inputs!$C$7 -> 0.15 | C51: =Inputs!$C$43*Inputs!$C$7 -> 0.15 | D51: =Inputs!$C$43*Inputs!$C$7 -> 0.15
A52: Etsy transaction fee £ | B52: =B46*Inputs!$C$44 -> 1.68675 | C52: =C46*Inputs!$C$44 -> 1.81675 | D52: =D46*Inputs!$C$44 -> 1.88175 | F52: 6.5% of item + shipping.
A53: Etsy Payments processing £ | B53: =B46*Inputs!$C$45+Inputs!$C$46 -> 1.238 | C53: =C46*Inputs!$C$45+Inputs!$C$46 -> 1.318 | D53: =D46*Inputs!$C$45+Inputs!$C$46 -> 1.358 | F53: 4% + £0.20.
A54: VAT on Etsy fees £ | B54: =(B51+B52+B53)*Inputs!$C$47 -> 0.61495 | C54: =(C51+C52+C53)*Inputs!$C$47 -> 0.65695 | D54: =(D51+D52+D53)*Inputs!$C$47 -> 0.67795 | F54: 20% on Etsy's fees.
A55: Returns / reprint allowance £ | B55: =B44*Inputs!$C$48 -> 1.1 | C55: =C44*Inputs!$C$48 -> 1.1 | D55: =D44*Inputs!$C$48 -> 1.1 | F55: Allowance on retail price.
A56: Total cost £ | B56: =B48+B49+B50+B51+B52+B53+B54+B55 -> 20.5322 | C56: =C48+C49+C50+C51+C52+C53+C54+C55 -> 20.7842 | D56: =D48+D49+D50+D51+D52+D53+D54+D55 -> 20.9102
A57: Contribution per order £ | B57: =B46-B56 -> 5.4178 | C57: =C46-C56 -> 7.1658 | D57: =D46-D56 -> 8.0398
A58: Margin on revenue | B58: =IF(B46=0,0,B57/B46) -> 0.20877842 | C58: =IF(C46=0,0,C57/C46) -> 0.25637925 | D58: =IF(D46=0,0,D57/D46) -> 0.2777133
A59: Same order on your own site with Stripe (no Etsy fees) £ | B59: =B46-B48-B49-B50-(B46*Inputs!$C$24+Inputs!$C$27)-B55 -> 8.51825 | C59: =C46-C48-C49-C50-(C46*Inputs!$C$25+Inputs!$C$27)-C55 -> 9.64975 | D59: =D46-D48-D49-D50-(D46*Inputs!$C$26+Inputs!$C$27)-D55 -> 10.416575 | F59: Higher margin, but you then handle VAT on goods sold to EU buyers yourself. Etsy first.
A61: One-off before launch (needs your OK) | B61: =Inputs!$C$49 -> 45 | F61: Order one sample of each item to check print quality and colour (Ember on Slate).
A63: Merch vs journals: contribution per sale (UK)
A64: Journal, after refunds | B64: =Journals!$J$6 -> 10.160467
A65: Tee, via Etsy | B65: =Merch!$B$19 -> 13.3993
A66: Art print, via Etsy | B66: =Merch!$B$38 -> 7.9578
A67: Notebook, via Etsy (estimate) | B67: =Merch!$B$57 -> 5.4178
A69: When merch is worth launching: per sale it earns about what a journal earns, but it needs samples, design and a second shop, people buy apparel from brands they already know, and returns and support are physical. Launch only after the gate on the Gates sheet (50 journal sales and visible demand). Until then journals win: the same reel sells a product with zero cost of goods that already exists.

Sheet Scenarios
A1: Scenarios: what a month looks like at the end of the 90 days
A2: Only today's numbers are measured. The funnel rates below are assumptions (blue), labelled; replace them with what the shop and guide page record after 30 days.
A4: Driver (per month) | B4: Conservative | C4: Base | D4: Optimistic | E4: Type and source
A5: Reels published per month | B5: 30 | C5: 30 | D5: 30 | E5: Plan: 1 reel a day (strategy/06-30-day-calendar.md).
A6: Views per reel by month 3 | B6: =Inputs!$C$12 -> 130 | C6: 400 | D6: 1000 | E6: Conservative = today's median (measured). Base = Phase 0 gate target (strategy/09). Optimistic = assumption.
A7: Profile/link clicks per 1,000 views | B7: 2 | C7: 4 | D7: 8 | E7: Assumption, not sourced. Week 1 of the monetisation plan measures it.
A8: Guide page visit to sign-up | B8: 0.2 | C8: 0.3 | D8: 0.4 | E8: Assumption, not sourced.
A9: Sign-up to journal purchase (within the 90 days) | B9: 0.01 | C9: 0.02 | D9: 0.04 | E9: Assumption, not sourced (the shop thread used no conversion benchmarks either).
A10: Share of clicks that go straight to the shop and buy | B10: 0.005 | C10: 0.01 | D10: 0.02 | E10: Assumption, not sourced.
A11: Affiliate clicks per 1,000 views | B11: 0.5 | C11: 1 | D11: 2 | E11: Assumption; starts in week 3 of the monetisation plan.
A13: Results at month-3 run rate
A14: Reel views | B14: =B5*B6 -> 3900 | C14: =C5*C6 -> 12000 | D14: =D5*D6 -> 30000
A15: Link clicks | B15: =B14/1000*B7 -> 7.8 | C15: =C14/1000*C7 -> 48 | D15: =D14/1000*D7 -> 240
A16: Guide sign-ups | B16: =B15*B8 -> 1.56 | C16: =C15*C8 -> 14.4 | D16: =D15*D8 -> 96
A17: Journal sales | B17: =B16*B9+B15*B10 -> 0.0546 | C17: =C16*C9+C15*C10 -> 0.768 | D17: =D16*D9+D15*D10 -> 8.64
A18: Journal sales £ (gross, VAT incl.) | B18: =B17*Journals!$B$6 -> 0.7644 | C18: =C17*Journals!$B$6 -> 10.752 | D18: =D17*Journals!$B$6 -> 120.96
A19: Journal contribution £ (after VAT, fees, refunds) | B19: =B17*Journals!$J$6 -> 0.55476148 | C19: =C17*Journals!$J$6 -> 7.8032384 | D19: =D17*Journals!$J$6 -> 87.786432
A20: Affiliate commission £ | B20: =B14/1000*B11*Inputs!$C$53*Inputs!$C$52*Inputs!$C$51 -> 0.117 | C20: =C14/1000*C11*Inputs!$C$53*Inputs!$C$52*Inputs!$C$51 -> 0.72 | D20: =D14/1000*D11*Inputs!$C$53*Inputs!$C$52*Inputs!$C$51 -> 3.6
A21: Total contribution £ | B21: =B19+B20 -> 0.67176148 | C21: =C19+C20 -> 8.5232384 | D21: =D19+D20 -> 91.386432
A22: Fixed costs £ (included set) | B22: ='Fixed costs'!$D$17 -> 28.224638 | C22: ='Fixed costs'!$D$17 -> 28.224638 | D22: ='Fixed costs'!$D$17 -> 28.224638
A23: Net result £ per month | B23: =B21-B22 -> -27.552876 | C23: =C21-C22 -> -19.701399 | D23: =D21-D22 -> 63.161794
A24: Net result € per month | B24: =B23*Inputs!$C$6 -> -31.685808 | C24: =C23*Inputs!$C$6 -> -22.656609 | D24: =D23*Inputs!$C$6 -> 72.636063
A25: Revenue per 1,000 views £ (gross) | B25: =IF(B14=0,0,(B18+B20)/B14*1000) -> 0.226 | C25: =IF(C14=0,0,(C18+C20)/C14*1000) -> 0.956 | D25: =IF(D14=0,0,(D18+D20)/D14*1000) -> 4.152
A26: Contribution per 1,000 views £ | B26: =IF(B14=0,0,B21/B14*1000) -> 0.17224653 | C26: =IF(C14=0,0,C21/C14*1000) -> 0.71026987 | D26: =IF(D14=0,0,D21/D14*1000) -> 3.0462144
A27: Value of one guide sign-up £ (journal only) | B27: =B9*Journals!$J$6 -> 0.10160467 | C27: =C9*Journals!$J$6 -> 0.20320933 | D27: =D9*Journals!$J$6 -> 0.40641867
A28: Views per month to cover fixed costs | B28: =IF(B26=0,0,B22/B26*1000) -> 163861.86 | C28: =IF(C26=0,0,C22/C26*1000) -> 39737.907 | D28: =IF(D26=0,0,D22/D26*1000) -> 9265.4797
A29: Journal sales per month to cover fixed costs | B29: =IF(Journals!$J$6=0,0,B22/Journals!$J$6) -> 2.7778879 | C29: =IF(Journals!$J$6=0,0,C22/Journals!$J$6) -> 2.7778879 | D29: =IF(Journals!$J$6=0,0,D22/Journals!$J$6) -> 2.7778879
A31: Today, measured: revenue per 1,000 views £ | B31: 0 | E31: Measured: £0 revenue on 1,347 reel views in the last 30 days (nothing is for sale yet).
A33: 90-day totals by scenario (from the P&L logic, shop live from the month set on Inputs)
A34: 90-day totals | B34: Conservative | C34: Base | D34: Optimistic | E34: Note
A35: Journal sales (units) | B35: =(IF(1>=Inputs!$C$76,Inputs!$C$10+(B14-Inputs!$C$10)/3,0)+IF(2>=Inputs!$C$76,Inputs!$C$10+(B14-Inputs!$C$10)*2/3,0)+IF(3>=Inputs!$C$76,B14,0))*(B7/1000*(B8*B9+B10)) -> 0.128058 | C35: =(IF(1>=Inputs!$C$76,Inputs!$C$10+(C14-Inputs!$C$10)/3,0)+IF(2>=Inputs!$C$76,Inputs!$C$10+(C14-Inputs!$C$10)*2/3,0)+IF(3>=Inputs!$C$76,C14,0))*(C7/1000*(C8*C9+C10)) -> 1.622208 | D35: =(IF(1>=Inputs!$C$76,Inputs!$C$10+(D14-Inputs!$C$10)/3,0)+IF(2>=Inputs!$C$76,Inputs!$C$10+(D14-Inputs!$C$10)*2/3,0)+IF(3>=Inputs!$C$76,D14,0))*(D7/1000*(D8*D9+D10)) -> 17.667936 | E35: Excludes the bundle and ads; the P&L sheet adds those for the selected scenario.
A36: Gross revenue £ | B36: =B35*Journals!$B$6+(3*Inputs!$C$10+(B14-Inputs!$C$10)*2)/1000*B11*Inputs!$C$53*Inputs!$C$52*Inputs!$C$51 -> 2.067222 | C36: =C35*Journals!$B$6+(3*Inputs!$C$10+(C14-Inputs!$C$10)*2)/1000*C11*Inputs!$C$53*Inputs!$C$52*Inputs!$C$51 -> 24.231732 | D36: =D35*Journals!$B$6+(3*Inputs!$C$10+(D14-Inputs!$C$10)*2)/1000*D11*Inputs!$C$53*Inputs!$C$52*Inputs!$C$51 -> 254.71274
A37: Contribution £ | B37: =B35*Journals!$J$6+(3*Inputs!$C$10+(B14-Inputs!$C$10)*2)/1000*B11*Inputs!$C$53*Inputs!$C$52*Inputs!$C$51 -> 1.575539 | C37: =C35*Journals!$J$6+(3*Inputs!$C$10+(C14-Inputs!$C$10)*2)/1000*C11*Inputs!$C$53*Inputs!$C$52*Inputs!$C$51 -> 18.00321 | D37: =D35*Journals!$J$6+(3*Inputs!$C$10+(D14-Inputs!$C$10)*2)/1000*D11*Inputs!$C$53*Inputs!$C$52*Inputs!$C$51 -> 186.87611
A38: Fixed costs £ | B38: =3*'Fixed costs'!$D$17 -> 84.673913 | C38: =3*'Fixed costs'!$D$17 -> 84.673913 | D38: =3*'Fixed costs'!$D$17 -> 84.673913
A39: Net result £ | B39: =B37-B38 -> -83.098374 | C39: =C37-C38 -> -66.670703 | D39: =D37-D38 -> 102.2022
A40: Net result € | B40: =B39*Inputs!$C$6 -> -95.56313 | C40: =C39*Inputs!$C$6 -> -76.671308 | D40: =D39*Inputs!$C$6 -> 117.53253

Sheet 90-day P&L
A1: 90-day P&L and cash (2 Nov 2026 to 31 Jan 2027)
A2: Day 1 is 2 Nov (bio link to Substack), first essay 5 Nov, day 90 is 31 Jan, aligned with substack/08-calendar-90-day.csv and the 30-day monetisation plan (community-agent/docs/06).
A3: Scenario (1 = conservative, 2 = base, 3 = optimistic) | B3: 2
A5: Line | B5: Nov 2026 (M1) | C5: Dec 2026 (M2) | D5: Jan 2027 (M3) | E5: 90-day total | F5: Note
A6: What happens this month | B6: Wk1 measure only; Wk2 DM keyword → guide; essays 1-4 from 5 Nov; Wk3 affiliate test; Wk4 first product push | C6: Day-30 review picks one experiment; essays weekly; €35 ad test only if the gate is met and you OK it | D6: Bundle only if 25 orders; day-90 review 31 Jan; decide next spends from Gates
A7: Month number | B7: 1 | C7: 2 | D7: 3
A8: Shop selling this month? (1/0) | B8: =IF(B7>=Inputs!$C$76,1,0) -> 1 | C8: =IF(C7>=Inputs!$C$76,1,0) -> 1 | D8: =IF(D7>=Inputs!$C$76,1,0) -> 1 | F8: From Inputs.
A9: Reel views | B9: =Inputs!$C$10+(INDEX(Scenarios!$B$14:$D$14,'90-day P&L'!$B$3)-Inputs!$C$10)*B7/3 -> 4898 | C9: =Inputs!$C$10+(INDEX(Scenarios!$B$14:$D$14,'90-day P&L'!$B$3)-Inputs!$C$10)*C7/3 -> 8449 | D9: =Inputs!$C$10+(INDEX(Scenarios!$B$14:$D$14,'90-day P&L'!$B$3)-Inputs!$C$10)*D7/3 -> 12000 | E9: =SUM(B9:D9) -> 25347 | F9: Ramps in a straight line from today's measured 30-day views to the scenario's month-3 level.
A10: Link clicks | B10: =B9/1000*INDEX(Scenarios!$B$7:$D$7,'90-day P&L'!$B$3) -> 19.592 | C10: =C9/1000*INDEX(Scenarios!$B$7:$D$7,'90-day P&L'!$B$3) -> 33.796 | D10: =D9/1000*INDEX(Scenarios!$B$7:$D$7,'90-day P&L'!$B$3) -> 48 | E10: =SUM(B10:D10) -> 101.388
A11: Guide sign-ups | B11: =B10*INDEX(Scenarios!$B$8:$D$8,'90-day P&L'!$B$3) -> 5.8776 | C11: =C10*INDEX(Scenarios!$B$8:$D$8,'90-day P&L'!$B$3) -> 10.1388 | D11: =D10*INDEX(Scenarios!$B$8:$D$8,'90-day P&L'!$B$3) -> 14.4 | E11: =SUM(B11:D11) -> 30.4164
A12: Journal sales | B12: =(B11*INDEX(Scenarios!$B$9:$D$9,'90-day P&L'!$B$3)+B10*INDEX(Scenarios!$B$10:$D$10,'90-day P&L'!$B$3))*B8 -> 0.313472 | C12: =(C11*INDEX(Scenarios!$B$9:$D$9,'90-day P&L'!$B$3)+C10*INDEX(Scenarios!$B$10:$D$10,'90-day P&L'!$B$3))*C8 -> 0.540736 | D12: =(D11*INDEX(Scenarios!$B$9:$D$9,'90-day P&L'!$B$3)+D10*INDEX(Scenarios!$B$10:$D$10,'90-day P&L'!$B$3))*D8 -> 0.768 | E12: =SUM(B12:D12) -> 1.622208
A13: Cumulative journal orders | B13: =B12+0 -> 0.313472 | C13: =C12+B13 -> 0.854208 | D13: =D12+C13 -> 1.622208 | E13: =D13 -> 1.622208
A14: Bundle sales (only after the order gate) | B14: =IF(0>=Inputs!$C$33,B12*0.3,0) -> 0 | C14: =IF(B13>=Inputs!$C$33,C12*0.3,0) -> 0 | D14: =IF(C13>=Inputs!$C$33,D12*0.3,0) -> 0 | E14: =SUM(B14:D14) -> 0 | F14: Assumption: 30% of buyers take the bundle once it exists. Not sourced.
A15: REVENUE (gross, VAT included)
A16: Journals £ | B16: =B12*Journals!$B$6 -> 4.388608 | C16: =C12*Journals!$B$6 -> 7.570304 | D16: =D12*Journals!$B$6 -> 10.752 | E16: =SUM(B16:D16) -> 22.710912
A17: Bundle £ | B17: =B14*Journals!$B$9 -> 0 | C17: =C14*Journals!$B$9 -> 0 | D17: =D14*Journals!$B$9 -> 0 | E17: =SUM(B17:D17) -> 0
A18: Affiliate commission £ | B18: =B9/1000*INDEX(Scenarios!$B$11:$D$11,'90-day P&L'!$B$3)*Inputs!$C$53*Inputs!$C$52*Inputs!$C$51 -> 0.29388 | C18: =C9/1000*INDEX(Scenarios!$B$11:$D$11,'90-day P&L'!$B$3)*Inputs!$C$53*Inputs!$C$52*Inputs!$C$51 -> 0.50694 | D18: =D9/1000*INDEX(Scenarios!$B$11:$D$11,'90-day P&L'!$B$3)*Inputs!$C$53*Inputs!$C$52*Inputs!$C$51 -> 0.72 | E18: =SUM(B18:D18) -> 1.52082
A19: Merch £ | B19: =0 -> 0 | C19: =0 -> 0 | D19: =0 -> 0 | E19: =SUM(B19:D19) -> 0 | F19: Not launched in the 90 days (gate not met).
A20: Brand deals, mentoring, paid Substack £ | B20: =0 -> 0 | C20: =0 -> 0 | D20: =0 -> 0 | E20: =SUM(B20:D20) -> 0 | F20: Not realistic at today's audience; see Other income for gates.
A21: Total revenue £ | B21: =SUM(B16:B20) -> 4.682488 | C21: =SUM(C16:C20) -> 8.077244 | D21: =SUM(D16:D20) -> 11.472 | E21: =SUM(B21:D21) -> 24.231732
A22: COST OF SALES
A23: VAT inside digital prices £ | B23: =(B16+B17)*(1-1/(1+Inputs!$C$22)) -> 0.73143467 | C23: =(C16+C17)*(1-1/(1+Inputs!$C$22)) -> 1.2617173 | D23: =(D16+D17)*(1-1/(1+Inputs!$C$22)) -> 1.792 | E23: =SUM(B23:D23) -> 3.785152 | F23: Collected and paid by Stripe as merchant of record.
A24: Payment fees £ | B24: =(B16+B17)/(1+Inputs!$C$22)-(B12*(Journals!$J$6+Journals!$B$6*Inputs!$C$29)+B14*(Journals!$J$9+Journals!$B$9*Inputs!$C$29)) -> 0.34049329 | C24: =(C16+C17)/(1+Inputs!$C$22)-(C12*(Journals!$J$6+Journals!$B$6*Inputs!$C$29)+C14*(Journals!$J$9+Journals!$B$9*Inputs!$C$29)) -> 0.58734744 | D24: =(D16+D17)/(1+Inputs!$C$22)-(D12*(Journals!$J$6+Journals!$B$6*Inputs!$C$29)+D14*(Journals!$J$9+Journals!$B$9*Inputs!$C$29)) -> 0.8342016 | E24: =SUM(B24:D24) -> 1.7620423 | F24: Blended Stripe + Managed Payments fees (Journals sheet).
A25: Refunds £ | B25: =(B16+B17)*Inputs!$C$29 -> 0.13165824 | C25: =(C16+C17)*Inputs!$C$29 -> 0.22710912 | D25: =(D16+D17)*Inputs!$C$29 -> 0.32256 | E25: =SUM(B25:D25) -> 0.68132736
A26: Cost of goods and postage £ | B26: =0 -> 0 | C26: =0 -> 0 | D26: =0 -> 0 | E26: =SUM(B26:D26) -> 0 | F26: Digital: £0. Becomes real only with merch or a print edition.
A27: Gross profit £ | B27: =B21-B23-B24-B25-B26 -> 3.4789018 | C27: =C21-C23-C24-C25-C26 -> 6.0010701 | D27: =D21-D23-D24-D25-D26 -> 8.5232384 | E27: =SUM(B27:D27) -> 18.00321
A28: OPERATING COSTS
A29: Metricool £ | B29: ='Fixed costs'!$D$5*'Fixed costs'!$F$5 -> 17.391304 | C29: ='Fixed costs'!$D$5*'Fixed costs'!$F$5 -> 17.391304 | D29: ='Fixed costs'!$D$5*'Fixed costs'!$F$5 -> 17.391304 | E29: =SUM(B29:D29) -> 52.173913
A30: Other fixed costs £ (domain, PO box, VPS, API if included) | B30: ='Fixed costs'!$D$17-B29 -> 10.833333 | C30: ='Fixed costs'!$D$17-C29 -> 10.833333 | D30: ='Fixed costs'!$D$17-D29 -> 10.833333 | E30: =SUM(B30:D30) -> 32.5 | F30: Domain amortised monthly here; paid upfront in the cash view.
A31: Paid ads £ (needs your OK per spend) | B31: 0 | C31: 0 | D31: 0 | E31: =SUM(B31:D31) -> 0 | F31: Blue cells: type a spend only after you approve it. €35 test ≈ £30.
A32: Total operating costs £ | B32: =B29+B30+B31 -> 28.224638 | C32: =C29+C30+C31 -> 28.224638 | D32: =D29+D30+D31 -> 28.224638 | E32: =SUM(B32:D32) -> 84.673913
A33: NET RESULT £ | B33: =B27-B32 -> -24.745736 | C33: =C27-C32 -> -22.223568 | D33: =D27-D32 -> -19.701399 | E33: =SUM(B33:D33) -> -66.670703
A34: Net result € | B34: =B33*Inputs!$C$6 -> -28.457596 | C34: =C33*Inputs!$C$6 -> -25.557103 | D34: =D33*Inputs!$C$6 -> -22.656609 | E34: =SUM(B34:D34) -> -76.671308
A35: CASH
A36: Opening cash £ | B36: =Inputs!$C$74 -> 0 | C36: =B40 -> -34.782128 | D36: =C40 -> -56.802904 | F36: M1 starts from Inputs 'Cash set aside'.
A37: Cash in £ (net of VAT/fees/refunds, after payout delay) | B37: =(B27+B26)*(1-Inputs!$C$75)+0*Inputs!$C$75 -> 2.6091764 | C37: =(C27+C26)*(1-Inputs!$C$75)+(B27+B26)*Inputs!$C$75 -> 5.370528 | D37: =(D27+D26)*(1-Inputs!$C$75)+(C27+C26)*Inputs!$C$75 -> 7.8926963 | E37: =SUM(B37:D37) -> 15.872401
A38: Cash out £ | B38: =B32-B30+B39 -> 37.391304 | C38: =C32-C30+C39 -> 27.391304 | D38: =D32-D30+D39 -> 27.391304 | E38: =SUM(B38:D38) -> 92.173913
A39: of which fixed costs paid this month £ | B39: =B30-'Fixed costs'!$D$6*'Fixed costs'!$F$6+IF(B7=1,'Fixed costs'!$C$6*'Fixed costs'!$F$6,0) -> 20 | C39: =C30-'Fixed costs'!$D$6*'Fixed costs'!$F$6+IF(C7=1,'Fixed costs'!$C$6*'Fixed costs'!$F$6,0) -> 10 | D39: =D30-'Fixed costs'!$D$6*'Fixed costs'!$F$6+IF(D7=1,'Fixed costs'!$C$6*'Fixed costs'!$F$6,0) -> 10 | E39: =SUM(B39:D39) -> 40 | F39: Domain's year paid in M1.
A40: Closing cash £ | B40: =B36+B37-B38 -> -34.782128 | C40: =C36+C37-C38 -> -56.802904 | D40: =D36+D37-D38 -> -76.301512 | E40: =D40 -> -76.301512
A42: Lowest closing cash in the 90 days £ | B42: =MIN(B40:D40) -> -76.301512 | F42: If this is below zero, the business needs that much from your own pocket over the period.

Sheet Ads
A1: Paid Instagram ads: what a result costs and what it is worth
A2: Rule: no spend happens without your OK for that specific spend. Benchmarks are aggregated 2026 figures with no UK split; your own ad screenshot replaces them.
A4: The €35 test (€5/day x 7 days, one winning reel) | B4: Expensive clicks | C4: Middle | D4: Cheap clicks | E4: Note
A5: Spend £ | B5: =Inputs!$C$35/Inputs!$C$6 -> 30.434783 | C5: =Inputs!$C$35/Inputs!$C$6 -> 30.434783 | D5: =Inputs!$C$35/Inputs!$C$6 -> 30.434783 | E5: €35 converted.
A6: Cost per link click £ | B6: =Inputs!$C$37*Inputs!$C$7 -> 1.35 | C6: =(Inputs!$C$36+Inputs!$C$37)/2*Inputs!$C$7 -> 0.825 | D6: =Inputs!$C$36*Inputs!$C$7 -> 0.3 | E6: Benchmark $0.40-1.80 converted; middle = average of the two.
A7: Link clicks | B7: =B5/B6 -> 22.544283 | C7: =C5/C6 -> 36.890646 | D7: =D5/D6 -> 101.44928
A8: Impressions at Reels CPM (for reference) | B8: =B5/(Inputs!$C$39*Inputs!$C$7)*1000 -> 5072.4638 | C8: =C5/((Inputs!$C$38+Inputs!$C$39)/2*Inputs!$C$7)*1000 -> 6763.285 | D8: =D5/(Inputs!$C$38*Inputs!$C$7)*1000 -> 10144.928 | E8: Benchmark Reels CPM $4-8.
A9: Guide page sign-up rate (base scenario) | B9: =Scenarios!$C$8 -> 0.3 | C9: =Scenarios!$C$8 -> 0.3 | D9: =Scenarios!$C$8 -> 0.3 | E9: Same assumption as organic.
A10: Guide sign-ups | B10: =B7*B9 -> 6.763285 | C10: =C7*C9 -> 11.067194 | D10: =D7*D9 -> 30.434783
A11: Cost per guide sign-up £ | B11: =IF(B10=0,0,B5/B10) -> 4.5 | C11: =IF(C10=0,0,C5/C10) -> 2.75 | D11: =IF(D10=0,0,D5/D10) -> 1
A12: Journal sales (sign-ups x purchase rate + direct buyers) | B12: =B10*Scenarios!$C$9+B7*Scenarios!$C$10 -> 0.36070853 | C12: =C10*Scenarios!$C$9+C7*Scenarios!$C$10 -> 0.59025033 | D12: =D10*Scenarios!$C$9+D7*Scenarios!$C$10 -> 1.6231884 | E12: Base-scenario assumptions.
A13: Cost per journal sale £ | B13: =IF(B12=0,0,B5/B12) -> 84.375 | C13: =IF(C12=0,0,C5/C12) -> 51.5625 | D13: =IF(D12=0,0,D5/D12) -> 18.75
A14: Followers if run as a profile-visit boost | B14: =B5/Inputs!$C$41 -> 20.289855 | C14: =C5/((Inputs!$C$40+Inputs!$C$41)/2) -> 33.816425 | D14: =D5/Inputs!$C$40 -> 101.44928 | E14: Assumed £0.30-1.50 per follower; not sourced.
A15: Cost per follower £ | B15: =IF(B14=0,0,B5/B14) -> 1.5 | C15: =IF(C14=0,0,C5/C14) -> 0.9 | D15: =IF(D14=0,0,D5/D14) -> 0.3
A16: Contribution earned back from journal sales £ | B16: =B12*Journals!$J$6 -> 3.664967 | C16: =C12*Journals!$J$6 -> 5.9972188 | D16: =D12*Journals!$J$6 -> 16.492352
A17: Return on spend | B17: =IF(B5=0,0,B16/B5) -> 0.12042035 | C17: =IF(C5=0,0,C16/C5) -> 0.19705147 | D17: =IF(D5=0,0,D16/D5) -> 0.54189156 | E17: Below 100% = the test costs money; it buys data, not profit.
A19: Break-even: the most a result can cost before ads lose money
A20: Max cost per journal sale £ (= contribution per sale) | B20: =Journals!$J$6 -> 10.160467
A21: Max cost per guide sign-up £ (= value of a sign-up, base scenario) | B21: =Scenarios!$C$27 -> 0.20320933 | E21: At a 2% purchase rate a sign-up is worth ~20p in journal profit within 90 days. Paid sign-ups only pay back once the list buys more than one product (bundle, Substack, later streams).
A23: Your ad results (from the screenshot you still owe)
A24: Spend £ | E24: Fill these from Instagram > Professional dashboard > Ad tools, or send the screenshot and Claude fills them.
A25: Impressions
A26: Reach
A27: Link clicks or results
A28: Followers gained
A29: Guide sign-ups attributed (src=ig_ad)
A30: Journal sales attributed
A31: Your cost per click £ | B31: =IF(N(B27)=0,"",B24/B27)
A32: Your cost per follower £ | B32: =IF(N(B28)=0,"",B24/B28)
A33: Your cost per guide sign-up £ | B33: =IF(N(B29)=0,"",B24/B29)
A34: Your cost per journal sale £ | B34: =IF(N(B30)=0,"",B24/B30)
A35: Your CPM £ | B35: =IF(N(B25)=0,"",B24/B25*1000)

Sheet Rate card
A1: Brand partnership rate card (tied to measured numbers only)
A2: Price = average views per reel ÷ 1,000 x creator CPM. Nano-tier floors apply only once you pass 1,000 followers. Every deal needs your OK, #ad disclosure (ASA/CAP), and the outreach rules in community-agent (PO box, consent).
A4: Inputs | B4: Today | C4: At the outreach gate | E4: Note
A5: Average views per reel | B5: =Inputs!$C$12 -> 130 | C5: 1000 | E5: Gate: median reel views ≥ 1,000 for 4 weeks (Gates sheet).
A6: Followers | B6: =Inputs!$C$9 -> 14 | C6: 1000
A7: Creator CPM low / high $ | B7: =Inputs!$C$59 -> 5 | C7: =Inputs!$C$60 -> 15 | E7: influee.co 2026: $5-15 per 1,000 views for nano/micro.
A9: Package | B9: Today low £ | C9: Today high £ | D9: At gate (low-high midpoint) £ | E9: How it's priced
A10: One reel (in-feed + reels tab) | B10: =$B$5/1000*$B$7*Inputs!$C$7*1 -> 0.4875 | C10: =$B$5/1000*$C$7*Inputs!$C$7*1 -> 1.4625 | D10: =MAX($C$5/1000*($B$7+$C$7)/2*Inputs!$C$7,IF($C$6>=1000,Inputs!$C$61*Inputs!$C$7,0))*1 -> 37.5 | E10: Base rate.
A11: Carousel (7 slides) | B11: =$B$5/1000*$B$7*Inputs!$C$7*0.8 -> 0.39 | C11: =$B$5/1000*$C$7*Inputs!$C$7*0.8 -> 1.17 | D11: =MAX($C$5/1000*($B$7+$C$7)/2*Inputs!$C$7,IF($C$6>=1000,Inputs!$C$61*Inputs!$C$7,0))*0.8 -> 30 | E11: 0.8x reel: lower reach on feed posts today (53 vs 1.1k views).
A12: Story set (3 frames, link sticker) | B12: =$B$5/1000*$B$7*Inputs!$C$7*0.5 -> 0.24375 | C12: =$B$5/1000*$C$7*Inputs!$C$7*0.5 -> 0.73125 | D12: =MAX($C$5/1000*($B$7+$C$7)/2*Inputs!$C$7,IF($C$6>=1000,Inputs!$C$61*Inputs!$C$7,0))*0.5 -> 18.75 | E12: 0.5x reel.
A13: Link in bio / links page for 7 days | B13: =$B$5/1000*$B$7*Inputs!$C$7*0.3 -> 0.14625 | C13: =$B$5/1000*$C$7*Inputs!$C$7*0.3 -> 0.43875 | D13: =MAX($C$5/1000*($B$7+$C$7)/2*Inputs!$C$7,IF($C$6>=1000,Inputs!$C$61*Inputs!$C$7,0))*0.3 -> 11.25 | E13: 0.3x reel.
A14: Substack sponsor line (per issue) | B14: =Inputs!$C$18*0.45/1000*25 -> 0 | C14: =B14 -> 0 | D14: =1000*0.45/1000*25 -> 11.25 | E14: Separate: subscribers x 45% opens ÷ 1,000 x £25 CPM (assumption). £0 until the publication exists.
A15: Usage rights for brand ads (per month) | B15: =$B$5/1000*$B$7*Inputs!$C$7*0.3 -> 0.14625 | C15: =$B$5/1000*$C$7*Inputs!$C$7*0.3 -> 0.43875 | D15: =MAX($C$5/1000*($B$7+$C$7)/2*Inputs!$C$7,IF($C$6>=1000,Inputs!$C$61*Inputs!$C$7,0))*0.3 -> 11.25 | E15: +30% of the package per month (common practice, assumption).
A16: Category exclusivity (per month) | B16: =$B$5/1000*$B$7*Inputs!$C$7*0.25 -> 0.121875 | C16: =$B$5/1000*$C$7*Inputs!$C$7*0.25 -> 0.365625 | D16: =MAX($C$5/1000*($B$7+$C$7)/2*Inputs!$C$7,IF($C$6>=1000,Inputs!$C$61*Inputs!$C$7,0))*0.25 -> 9.375 | E16: +25% (assumption).
A18: Sellable today? | B18: =IF(AND(Inputs!$C$9>=1000,Inputs!$C$12>=1000),"Yes","Not yet") -> Not yet | E18: At today's numbers a reel is worth about £0.50-1.50 to a sponsor, so outreach would cost more in time than it earns.
A20: Category (from the sponsorship CRM) | B20: Fit | E20: Notes and red lines
A21: Stationery (notebooks, pens, planners) | B21: Strong | E21: Natural fit with journaling; also merch overlap.
A22: Books and publishers (philosophy, psychology) | B22: Strong | E22: Affiliate first, sponsored reading lists later.
A23: Education (courses, learning platforms) | B23: Good | E23: Only reputable providers; no 'get rich' courses.
A24: Mindfulness and meditation apps | B24: Good | E24: No clinical or therapy claims; you are not a therapist.
A25: Productivity software | B25: Medium | E25: Fits the Tools highlight; avoid hustle framing.
A26: Men's grooming | B26: Weak | E26: Off-positioning: the brand is not men-only or young-men framed.
A27: Accessories (watches, bags) | B27: Medium | E27: Only minimal, slow-design brands; no luxury flexing.
A28: Professional development | B28: Good | E28: Coaching platforms, writing tools.
A29: Never | B29: No | E29: Gambling, crypto, supplements, alcohol, payday loans, red-pill content, anything making health claims.

Sheet Other income
A1: Other income streams: margin, effort, threshold and order
A2: Contribution excludes your time (effort captures that). 'Volume at gate' is a deliberately small assumption for the first month after the gate is met. Score = monthly contribution at gate ÷ effort; rank 1 = do first.
A4: Stream | B4: Price £ | C4: Fees + COGS per unit £ | D4: Contribution per unit £ | E4: Margin | F4: Effort (1-5) | G4: Gate before it's realistic | H4: Units/month at gate | I4: Monthly contribution at gate £ | J4: Score | K4: Rank | L4: Horizon | M4: Notes and risks
A5: Journal + digital products | B5: =Journals!$B$6 -> 14 | C5: =Journals!$B$6-Journals!$J$6 -> 3.8395333 | D5: =B5-C5 -> 10.160467 | E5: =IF(B5=0,0,D5/B5) -> 0.72574762 | F5: 1 | G5: Shop live (already built, test mode) | H5: 3 | I5: =D5*H5 -> 30.4814 | J5: =I5/F5 -> 30.4814 | K5: =RANK(J5,$J$5:$J$16) -> 6 | L5: 90 days | M5: Built and priced by the shop thread. Zero cost of goods.
A6: Affiliate links (books, stationery) | B6: =Inputs!$C$52 -> 12 | C6: =Inputs!$C$52*(1-Inputs!$C$51) -> 10.8 | D6: =B6-C6 -> 1.2 | E6: =IF(B6=0,0,D6/B6) -> 0.1 | F6: 1 | G6: Any reach; Week 3 of the monetisation plan | H6: 2 | I6: =D6*H6 -> 2.4 | J6: =I6/F6 -> 2.4 | K6: =RANK(J6,$J$5:$J$16) -> 12 | L6: 90 days | M6: Tiny money; useful mainly to measure buying intent. #ad disclosure.
A7: Print edition of the journal (KDP) | B7: =Inputs!$C$70 -> 12.99 | C7: =Inputs!$C$70-Journals!$B$17 -> 7.486 | D7: =B7-C7 -> 5.504 | E7: =IF(B7=0,0,D7/B7) -> 0.42371055 | F7: 2 | G7: 50 digital sales or repeated requests for print | H7: 3 | I7: =D7*H7 -> 16.512 | J7: =I7/F7 -> 8.256 | K7: =RANK(J7,$J$5:$J$16) -> 11 | L7: 3-6 months | M7: No stock; Amazon prints and posts. Cost of goods = printing.
A8: Merch (POD tee via Etsy) | B8: =Merch!$B$6+Merch!$B$7 -> 31.95 | C8: =(Merch!$B$6+Merch!$B$7)-Merch!$B$19 -> 18.5507 | D8: =B8-C8 -> 13.3993 | E8: =IF(B8=0,0,D8/B8) -> 0.41938341 | F8: 2 | G8: 50 journal sales + people asking for merch | H8: 3 | I8: =D8*H8 -> 40.1979 | J8: =I8/F8 -> 20.09895 | K8: =RANK(J8,$J$5:$J$16) -> 8 | L8: 4-6 months | M8: Physical returns and support; needs samples (~£45).
A9: Brand partnerships / sponsored posts | B9: ='Rate card'!$D$10 -> 37.5 | C9: ='Rate card'!$D$10*0.05 -> 1.875 | D9: =B9-C9 -> 35.625 | E9: =IF(B9=0,0,D9/B9) -> 0.95 | F9: 3 | G9: ≥1,000 followers, median reel views ≥1,000 for 4 weeks, PO box, media kit | H9: 1 | I9: =D9*H9 -> 35.625 | J9: =I9/F9 -> 11.875 | K9: =RANK(J9,$J$5:$J$16) -> 10 | L9: 4-8 months | M9: Rate card ties price to measured views. Each deal needs your OK.
A10: Live online workshop (90 min) | B10: =Inputs!$C$65 -> 15 | C10: =Inputs!$C$65*Inputs!$C$24+Inputs!$C$27 -> 0.425 | D10: =B10-C10 -> 14.575 | E10: =IF(B10=0,0,D10/B10) -> 0.97166667 | F10: 3 | G10: ≥500 on the email list | H10: 15 | I10: =D10*H10 -> 218.625 | J10: =I10/F10 -> 72.875 | K10: =RANK(J10,$J$5:$J$16) -> 1 | L10: 4-6 months | M10: Free tools (Google Meet). Record it to become course material.
A11: Paid Substack tier | B11: =Inputs!$C$54 -> 5 | C11: =Inputs!$C$54*(Inputs!$C$55+Inputs!$C$56)+Inputs!$C$57 -> 0.895 | D11: =B11-C11 -> 4.105 | E11: =IF(B11=0,0,D11/B11) -> 0.821 | F11: 3 | G11: 1,000 free subscribers, ≥45% opens (Substack plan) | H11: =1000*Inputs!$C$58 -> 30 | I11: =D11*H11 -> 123.15 | J11: =I11/F11 -> 41.05 | K11: =RANK(J11,$J$5:$J$16) -> 4 | L11: 6-12 months | M11: Recurring, but needs a weekly paid-only piece you'd keep up.
A12: Small-group reflective mentoring (cohort of 6) | B12: =Inputs!$C$64 -> 60 | C12: =Inputs!$C$64*Inputs!$C$24+Inputs!$C$27 -> 1.1 | D12: =B12-C12 -> 58.9 | E12: =IF(B12=0,0,D12/B12) -> 0.98166667 | F12: 4 | G12: ≥1,000 list + 10 people asking | H12: 3 | I12: =D12*H12 -> 176.7 | J12: =I12/F12 -> 44.175 | K12: =RANK(J12,$J$5:$J$16) -> 2 | L12: 6-9 months | M12: Not therapy: reflective mentoring with a clear scope, signposting to professionals, no crisis work. Breaks anonymity unless run under the brand voice only.
A13: 1:1 reflective mentoring (50 min) | B13: =Inputs!$C$63 -> 45 | C13: =Inputs!$C$63*Inputs!$C$24+Inputs!$C$27 -> 0.875 | D13: =B13-C13 -> 44.125 | E13: =IF(B13=0,0,D13/B13) -> 0.98055556 | F13: 5 | G13: ≥1,000 list + 10 people asking | H13: 4 | I13: =D13*H13 -> 176.5 | J13: =I13/F13 -> 35.3 | K13: =RANK(J13,$J$5:$J$16) -> 5 | L13: 6-9 months | M13: Same scope limits. Consider professional indemnity insurance (~£10-15/mo, assumption) before the first paid session.
A14: Paid community / membership | B14: =Inputs!$C$67 -> 6 | C14: =Inputs!$C$67*(Inputs!$C$55+Inputs!$C$56)+Inputs!$C$57 -> 1.024 | D14: =B14-C14 -> 4.976 | E14: =IF(B14=0,0,D14/B14) -> 0.82933333 | F14: 4 | G14: 300+ engaged newsletter readers (monetisation plan) | H14: 15 | I14: =D14*H14 -> 74.64 | J14: =I14/F14 -> 18.66 | K14: =RANK(J14,$J$5:$J$16) -> 9 | L14: 9-12 months | M14: Ongoing moderation load; overlaps paid Substack, so pick one.
A15: Self-paced course | B15: =Inputs!$C$66 -> 49 | C15: =Inputs!$C$66-Inputs!$C$66/(1+Inputs!$C$22)+Inputs!$C$66*(Inputs!$C$24+Inputs!$C$23)+Inputs!$C$27 -> 10.816667 | D15: =B15-C15 -> 38.183333 | E15: =IF(B15=0,0,D15/B15) -> 0.7792517 | F15: 5 | G15: ≥1,000 list + 50 journal buyers | H15: 3 | I15: =D15*H15 -> 114.55 | J15: =I15/F15 -> 22.91 | K15: =RANK(J15,$J$5:$J$16) -> 7 | L15: 9-12 months | M15: Sold through the same shop (VAT handled). Big build.
A16: Licensing the content system to other brands | B16: =Inputs!$C$68 -> 250 | C16: =Inputs!$C$69 -> 30 | D16: =B16-C16 -> 220 | E16: =IF(B16=0,0,D16/B16) -> 0.88 | F16: 5 | G16: Moodius meets Phase 0 gates and the engine is productised (strategy/09 Phase 1) | H16: 1 | I16: =D16*H16 -> 220 | J16: =I16/F16 -> 44 | K16: =RANK(J16,$J$5:$J$16) -> 3 | L16: 12+ months | M16: Contracts, support, IP. Only after the engine runs 2-3 of your own brands.

Sheet Gates
A1: Unlock thresholds: what has to be true before the next spend or stream
A2: Current values link to Inputs; update Inputs weekly and the status updates itself. A met gate still needs your OK for any spend.
A4: Gate | B4: What it unlocks | C4: Current | D4: Target | E4: Status | F4: Why this number
A5: Shop live | B5: Product reels P001-P006, journal revenue | C5: =Inputs!$C$20 -> 0 | D5: 1 | E5: =IF(C5="","No data",IF(C5>=D5,"Met","Not yet")) -> Not yet | F5: Nothing can be sold before this.
A6: Organic guide sign-ups (cumulative) | B6: €35 ad test (with your OK) | C6: =Inputs!$C$16 -> 0 | D6: 25 | E6: =IF(C6="","No data",IF(C6>=D6,"Met","Not yet")) -> Not yet | F6: Proves the guide page converts organically, so an ad isn't buying the first-ever test.
A7: A reel at ≥2x the median views | B7: Pick the ad creative | C7: =Inputs!$C$13 -> 278 | D7: =2*Inputs!$C$12 -> 260 | E7: =IF(C7="","No data",IF(C7>=D7,"Met","Not yet")) -> Met | F7: Proxy uses the best day's reel views. Boost a proven reel, never an untested one.
A8: Ad test cost per sign-up ≤ 3x a sign-up's value | B8: Second ad round (€70-100, with your OK) | D8: =3*Ads!$B$21 -> 0.609628 | E8: =IF(C8="","No data",IF(C8<=D8,"Met","Not yet")) -> No data | F8: Enter your result from the Ads sheet. 3x allows for the bundle and later streams.
A9: Journal orders | B9: Build the £29 bundle | C9: =Inputs!$C$17 -> 0 | D9: =Inputs!$C$33 -> 25 | E9: =IF(C9="","No data",IF(C9>=D9,"Met","Not yet")) -> Not yet | F9: Shop thread's rule (or 6 weeks on sale).
A10: Journal orders | B10: Merch samples (~£45) and the print edition | C10: =Inputs!$C$17 -> 0 | D10: 50 | E10: =IF(C10="","No data",IF(C10>=D10,"Met","Not yet")) -> Not yet | F10: Proof people pay for the brand before adding physical products.
A11: Comments + story replies per week | B11: VPS + Claude API for comment replies (€6-15/mo) | C11: =Inputs!$C$19 -> 0 | D11: 20 | E11: =IF(C11="","No data",IF(C11>=D11,"Met","Not yet")) -> Not yet | F11: Below this you answer by hand in a few minutes a day.
A12: Followers | B12: Brand outreach (plus PO box and 4 weeks of data) | C12: =Inputs!$C$9 -> 14 | D12: 1000 | E12: =IF(C12="","No data",IF(C12>=D12,"Met","Not yet")) -> Not yet | F12: Nano tier starts at 1,000; brands check this first.
A13: Median reel views | B13: Brand outreach; base-scenario revenue | C13: =Inputs!$C$12 -> 130 | D13: 1000 | E13: =IF(C13="","No data",IF(C13>=D13,"Met","Not yet")) -> Not yet | F13: At this level the rate card prices a reel at ~£37 (nano floor); below it outreach isn't worth the time.
A14: Median reel views | B14: Phase 0 → Phase 1 of the scaling roadmap | C14: =Inputs!$C$12 -> 130 | D14: 400 | E14: =IF(C14="","No data",IF(C14>=D14,"Met","Not yet")) -> Not yet | F14: strategy/09 gate (3 weeks in a row).
A15: Email list (guide + Substack) | B15: Live workshop pilot | C15: =Inputs!$C$16+Inputs!$C$18 -> 0 | D15: 500 | E15: =IF(C15="","No data",IF(C15>=D15,"Met","Not yet")) -> Not yet | F15: ~3% of a list buying a £15 ticket ≈ 15 seats.
A16: Substack free subscribers | B16: Paid Substack tier | C16: =Inputs!$C$18 -> 0 | D16: 1000 | E16: =IF(C16="","No data",IF(C16>=D16,"Met","Not yet")) -> Not yet | F16: Substack plan gate; at 3% conversion that's ~30 paying.
A17: Email list (guide + Substack) | B17: Mentoring pilot (small group first) | C17: =Inputs!$C$16+Inputs!$C$18 -> 0 | D17: 1000 | E17: =IF(C17="","No data",IF(C17>=D17,"Met","Not yet")) -> Not yet | F17: Plus 10 people asking unprompted.
A18: Engaged newsletter readers | B18: Paid community / membership | C18: =Inputs!$C$18*0.3 -> 0 | D18: 300 | E18: =IF(C18="","No data",IF(C18>=D18,"Met","Not yet")) -> Not yet | F18: Monetisation plan gate; engaged ≈ 30% of subscribers (assumption).
A19: Months with contribution ≥ fixed costs | B19: Any new recurring cost | D19: 2 | E19: =IF(C19="","No data",IF(C19>=D19,"Met","Not yet")) -> No data | F19: Enter the count from your monthly review; keeps the business self-funding.
A21: Gates met | C21: =COUNTIF(E5:E19,"Met") -> 1 | D21: =ROWS(E5:E19) -> 15

Sheet 12-month plan
A1: 12-month sequence (gated: a step moves when its gate is met, not on the date)
A3: Months | B3: Focus | C3: Income active or tested | D3: Spend that may unlock (each needs your OK)
A4: Nov 2026 | B4: Shop live, guide page, DM keyword funnel, essays weekly from 5 Nov | C4: Journal, affiliate test | D4: Domain £10/yr, PO box ~£10/mo
A5: Dec 2026 | B5: Day-30 review; holiday gift edition push | C5: Journal, gift edition, affiliate | D5: €35 ad test if 25 organic sign-ups
A6: Jan 2027 | B6: Day-90 review (31 Jan); Substack vs Ghost revisit 30 Jan | C6: Journal; bundle if 25 orders | D6: Second ad round only if the test passed
A7: Feb-Mar 2027 | B7: Bundle + workbooks; Phase 1 engine productisation if Phase 0 met | C7: Journal, bundle, upgrade | D7: VPS + Claude API if comments ≥ 20/week
A8: Apr-Jun 2027 | B8: Print edition and merch pilot if 50 orders; first brand deals if 1k followers / 1k views | C8: + print edition, merch, sponsored posts, workshop pilot | D8: Merch samples ~£45; Etsy listings
A9: Jul-Sep 2027 | B9: Paid Substack if 1,000 free; small-group mentoring pilot | C9: + paid Substack, mentoring | D9: Insurance before paid mentoring
A10: Oct 2027 | B10: 12-month review; decide membership vs course; brands 2-3 | C10: + membership or course | D10: Metricool upgrade for more brands (strategy/09)
A11: 12+ months | B11: Licensing the content system once it runs 2-3 of your own brands | C11: + licensing | D11: Legal review of a licence contract

Sheet Your inputs
A1: What only Surafel can provide
A3: Input | B3: Where it goes | C3: Why | D3: Status
A4: Ad results screenshot | B4: Ads sheet, yellow cells | C4: Replaces the benchmark cost per click/follower with your real numbers. | D4: Owed
A5: Approve domain (£10/yr) and PO box (£5-15/mo) | B5: Fixed costs: Include column | C5: Both are switched on in the model already; set to 0 if you decline. | D5: Pending
A6: OK for VPS + Claude API (€6-15/mo) | B6: Fixed costs: Include column | C6: Off until the comments gate is met. | D6: Pending
A7: Shop live date | B7: Inputs: Shop live month, Shop live flag | C7: Revenue starts that month. | D7: Pending
A8: Starting cash / budget for the business | B8: Inputs: Cash set aside | C8: Shows whether cash ever goes negative. | D8: Pending
A9: Real Stripe fees and payout schedule once live | B9: Inputs: Stripe rows, payout delay | C9: Benchmarks today; your statements later. | D9: After launch
A10: Buyer country mix | B10: Inputs: Buyer mix | C10: From Stripe after ~25 sales. | D10: After launch
A11: Merch supplier choice and real base costs | B11: Merch sheet, blue cells | C11: Printful prices shown; Printify/Gelato differ. Notebook price is an estimate. | D11: Later
A12: Where you're tax-resident and whether you're VAT-registered | B12: Tell Claude (affects Merch and own-site sales) | C12: Stripe Managed Payments and Etsy cover VAT on sales; your income tax isn't modelled. Check with an accountant. | D12: Open
A13: Weekly numbers: sign-ups, orders, comments, Substack subs | B13: Inputs: Measured section | C13: Drives the Gates sheet. | D13: Weekly
A14: Mentoring yes/no (it may break anonymity) | B14: Other income | C14: Positioned as reflective mentoring, not therapy. | D14: Later
A15: Exchange rates | B15: Inputs: Currency | C15: Set to approximate 21 Oct 2026 values. | D15: Optional

Sheet Sources
A1: Sources
A3: Metricool analytics (measured) | B3: brand 7224060, IGEV01/05/23/39, pulled 21 Oct 2026
A4: Journal pricing and fees | B4: business/pricing/margins.py and margins.csv (digital-products thread); stripe.com/gb/pricing; support.stripe.com/questions/managed-payments-pricing
A5: Instagram ad CPC/CPM 2026 | B5: https://topgrowthmarketing.com/instagram-ads-cost/ (updated 25 Sep 2026; aggregates AdBacklog, WordStream, Ryze.AI, WebFX)
A6: Printful tee base + shipping | B6: https://podvector.ai/articles/printful/costs-and-charges/printful-bella-canvas-3001-price-shipping-time-full-breakdown-for-pod-sellers (May 2026)
A7: Printful poster base + shipping | B7: https://podvector.ai/articles/printful/costs-and-charges/printful-poster-pricing-full-breakdown-for-pod-sellers (May 2026)
A8: Gelato pricing | B8: https://ecommerce-platforms.com/articles/gelato-print-on-demand-pricing (Gelato+ $19.99-29.99/mo; base costs only in dashboard)
A9: Creator rates | B9: https://influee.co/gb/blog/instagram-influencer-pricing (Mar 2026; directional ranges)
A10: Substack conversion and fees | B10: https://bestwriting.com/substack-statistics; substack/10-costs-and-apis.md
A11: Bookshop.org affiliate | B11: https://www.supadu.com/blogs/news-and-views/bookshop-org
A12: Etsy fees | B12: etsy.com/legal/fees (listing $0.20, 6.5% transaction, Etsy Payments UK 4% + £0.20); check before launch
A13: Gates and plans | B13: strategy/09-scaling-roadmap.md; community-agent/docs/06-monetisation-30-day.md; business/funnel/bundle-plan.md; substack/08-calendar-90-day.csv
